task1/lsfr7.sv
module lsfr7 (
    input logic clk,
    input logic rst,
    input logic en,
    output logic [6:0] dout
);

logic [6:0] reg7;

always_ff@(posedge clk)
    if (rst) reg7 <= {6'b0, en};
    else reg7 <= {reg7[5:0], reg7[6]^reg7[2]};

assign dout = reg7;
endmodule

task1/lsfr4.vcd
$version Generated by VerilatedVcd $end
$timescale 1ps $end
 $scope module TOP $end
  $var wire 1 # clk $end
  $var wire 1 $ rst $end
  $var wire 1 % en $end
  $var wire 7 & dout [6:0] $end
  $scope module lsfr7 $end
   $var wire 1 # clk $end
   $var wire 1 $ rst $end
   $var wire 1 % en $end
   $var wire 7 & dout [6:0] $end
   $var wire 7 ' reg7 [6:0] $end
  $upscope $end
 $upscope $end
$enddefinitions $end


#0
1#
0$
1%
b0000000 &
b0000000 '
#1
0#
#2
1#
1$
#3
0#
#4
1#
0$
b0000001 &
b0000001 '
#5
0#
#6
1#
b0000010 &
b0000010 '
#7
0#
#8
1#
b0000100 &
b0000100 '
#9
0#
#10
1#
b0001001 &
b0001001 '
#11
0#
#12
1#
b0010010 &
b0010010 '
#13
0#
#14
1#
b0100100 &
b0100100 '
#15
0#
#16
1#
b1001001 &
b1001001 '
#17
0#
#18
1#
b0010011 &
b0010011 '
#19
0#
#20
1#
b0100110 &
b0100110 '
#21
0#
#22
1#
b1001101 &
b1001101 '
#23
0#
#24
1#
b0011010 &
b0011010 '
#25
0#
#26
1#
b0110100 &
b0110100 '
#27
0#
#28
1#
b1101001 &
b1101001 '
#29
0#
#30
1#
b1010011 &
b1010011 '
#31
0#
#32
1#
b0100111 &
b0100111 '
#33
0#
#34
1#
b1001111 &
b1001111 '
#35
0#
#36
1#
b0011110 &
b0011110 '
#37
0#
#38
1#
b0111101 &
b0111101 '
#39
0#
#40
1#
b1111011 &
b1111011 '
#41
0#
#42
1#
b1110111 &
b1110111 '
#43
0#
#44
1#
b1101110 &
b1101110 '
#45
0#
#46
1#
b1011100 &
b1011100 '
#47
0#
#48
1#
b0111000 &
b0111000 '
#49
0#
#50
1#
b1110000 &
b1110000 '
#51
0#
#52
1#
b1100001 &
b1100001 '
#53
0#
#54
1#
b1000011 &
b1000011 '
#55
0#
#56
1#
b0000111 &
b0000111 '
#57
0#
#58
1#
b0001111 &
b0001111 '
#59
0#
#60
1#
b0011111 &
b0011111 '
#61
0#
#62
1#
b0111111 &
b0111111 '
#63
0#
#64
1#
b1111111 &
b1111111 '
#65
0#
#66
1#
b1111110 &
b1111110 '
#67
0#
#68
1#
b1111100 &
b1111100 '
#69
0#
#70
1#
b1111000 &
b1111000 '
#71
0#
#72
1#
b1110001 &
b1110001 '
#73
0#
#74
1#
b1100011 &
b1100011 '
#75
0#
#76
1#
b1000111 &
b1000111 '
#77
0#
#78
1#
b0001110 &
b0001110 '
#79
0#
#80
1#
b0011101 &
b0011101 '
#81
0#
#82
1#
b0111011 &
b0111011 '
#83
0#
#84
1#
b1110110 &
b1110110 '
#85
0#
#86
1#
b1101100 &
b1101100 '
#87
0#
#88
1#
b1011000 &
b1011000 '
#89
0#
#90
1#
b0110001 &
b0110001 '
#91
0#
#92
1#
b1100010 &
b1100010 '
#93
0#
#94
1#
b1000101 &
b1000101 '
#95
0#
#96
1#
b0001010 &
b0001010 '
#97
0#
#98
1#
b0010100 &
b0010100 '
#99
0#
#100
1#
b0101001 &
b0101001 '
#101
0#
#102
1#
b1010010 &
b1010010 '
#103
0#
#104
1#
b0100101 &
b0100101 '
#105
0#
#106
1#
b1001011 &
b1001011 '
#107
0#
#108
1#
b0010111 &
b0010111 '
#109
0#
#110
1#
b0101111 &
b0101111 '
#111
0#
#112
1#
b1011111 &
b1011111 '
#113
0#
#114
1#
b0111110 &
b0111110 '
#115
0#
#116
1#
b1111101 &
b1111101 '
#117
0#
#118
1#
b1111010 &
b1111010 '
#119
0#
#120
1#
b1110101 &
b1110101 '
#121
0#
#122
1#
b1101010 &
b1101010 '
#123
0#
#124
1#
b1010101 &
b1010101 '
#125
0#
#126
1#
b0101010 &
b0101010 '
#127
0#
#128
1#
b1010100 &
b1010100 '
#129
0#
#130
1#
b0101000 &
b0101000 '
#131
0#
#132
1#
b1010000 &
b1010000 '
#133
0#
#134
1#
b0100001 &
b0100001 '
#135
0#
#136
1#
b1000010 &
b1000010 '
#137
0#
#138
1#
b0000101 &
b0000101 '
#139
0#
#140
1#
b0001011 &
b0001011 '
#141
0#
#142
1#
b0010110 &
b0010110 '
#143
0#
#144
1#
b0101101 &
b0101101 '
#145
0#
#146
1#
b1011011 &
b1011011 '
#147
0#
#148
1#
b0110111 &
b0110111 '
#149
0#
#150
1#
b1101111 &
b1101111 '
#151
0#
#152
1#
b1011110 &
b1011110 '
#153
0#
#154
1#
b0111100 &
b0111100 '
#155
0#
#156
1#
b1111001 &
b1111001 '
#157
0#
#158
1#
b1110011 &
b1110011 '
#159
0#
#160
1#
b1100111 &
b1100111 '
#161
0#
#162
1#
b1001110 &
b1001110 '
#163
0#
#164
1#
b0011100 &
b0011100 '
#165
0#
#166
1#
b0111001 &
b0111001 '
#167
0#
#168
1#
b1110010 &
b1110010 '
#169
0#
#170
1#
b1100101 &
b1100101 '
#171
0#
#172
1#
b1001010 &
b1001010 '
#173
0#
#174
1#
b0010101 &
b0010101 '
#175
0#
#176
1#
b0101011 &
b0101011 '
#177
0#
#178
1#
b1010110 &
b1010110 '
#179
0#
#180
1#
b0101100 &
b0101100 '
#181
0#
#182
1#
b1011001 &
b1011001 '
#183
0#
#184
1#
b0110011 &
b0110011 '
#185
0#
#186
1#
b1100110 &
b1100110 '
#187
0#
#188
1#
b1001100 &
b1001100 '
#189
0#
#190
1#
b0011000 &
b0011000 '
#191
0#
#192
1#
b0110000 &
b0110000 '
#193
0#
#194
1#
b1100000 &
b1100000 '
#195
0#
#196
1#
b1000001 &
b1000001 '
#197
0#
#198
1#
b0000011 &
b0000011 '
