task2/f1_fsm.sv
module f1_fsm (
    input logic clk,
    input logic rst,
    input logic en,
    output logic [7:0] dout
);

typedef enum{S0, S1, S2, S3, S4, S5, S6, S7, S8} state;
state current, next;

always_ff@(posedge clk)
    if (rst) current <= S0;
    else if (en) current <= next;

always_comb
    case (current)
        S0: next = S1;
        S1: next = S2;
        S2: next = S3;
        S3: next = S4;
        S4: next = S5;
        S5: next = S6;
        S6: next = S7;
        S7: next = S8;
        S7: next = S0;
        default next = S0;
    endcase

always_comb
    case (current)
        S0: dout = 8'b00000000;
        S1: dout = 8'b00000001;
        S2: dout = 8'b00000011;
        S3: dout = 8'b00000111;
        S4: dout = 8'b00001111;
        S5: dout = 8'b00011111;
        S6: dout = 8'b00111111;
        S7: dout = 8'b01111111;
        S8: dout = 8'b11111111;
    endcase



// state unit

endmodule

task2/Vf1_fsm.vcd
$version Generated by VerilatedVcd $end
$timescale 1ps $end
 $scope module TOP $end
  $var wire 1 # clk $end
  $var wire 1 $ rst $end
  $var wire 1 % en $end
  $var wire 8 & dout [7:0] $end
  $scope module f1_fsm $end
   $var wire 1 # clk $end
   $var wire 1 $ rst $end
   $var wire 1 % en $end
   $var wire 8 & dout [7:0] $end
   $var wire 32 ' current [31:0] $end
   $var wire 32 ( next [31:0] $end
  $upscope $end
 $upscope $end
$enddefinitions $end


#0
1#
0$
1%
b00000000 &
b00000000000000000000000000000000 '
b00000000000000000000000000000001 (
#1
0#
#2
1#
1$
b00000001 &
b00000000000000000000000000000001 '
b00000000000000000000000000000010 (
#3
0#
#4
1#
0$
b00000000 &
b00000000000000000000000000000000 '
b00000000000000000000000000000001 (
#5
0#
#6
1#
b00000001 &
b00000000000000000000000000000001 '
b00000000000000000000000000000010 (
#7
0#
#8
1#
b00000011 &
b00000000000000000000000000000010 '
b00000000000000000000000000000011 (
#9
0#
#10
1#
b00000111 &
b00000000000000000000000000000011 '
b00000000000000000000000000000100 (
#11
0#
#12
1#
b00001111 &
b00000000000000000000000000000100 '
b00000000000000000000000000000101 (
#13
0#
#14
1#
b00011111 &
b00000000000000000000000000000101 '
b00000000000000000000000000000110 (
#15
0#
#16
1#
b00111111 &
b00000000000000000000000000000110 '
b00000000000000000000000000000111 (
#17
0#
#18
1#
b01111111 &
b00000000000000000000000000000111 '
b00000000000000000000000000001000 (
#19
0#
#20
1#
b11111111 &
b00000000000000000000000000001000 '
b00000000000000000000000000000000 (
#21
0#
#22
1#
b00000000 &
b00000000000000000000000000000000 '
b00000000000000000000000000000001 (
#23
0#
#24
1#
b00000001 &
b00000000000000000000000000000001 '
b00000000000000000000000000000010 (
#25
0#
#26
1#
b00000011 &
b00000000000000000000000000000010 '
b00000000000000000000000000000011 (
#27
0#
#28
1#
b00000111 &
b00000000000000000000000000000011 '
b00000000000000000000000000000100 (
#29
0#
#30
1#
b00001111 &
b00000000000000000000000000000100 '
b00000000000000000000000000000101 (
#31
0#
#32
1#
b00011111 &
b00000000000000000000000000000101 '
b00000000000000000000000000000110 (
#33
0#
#34
1#
b00111111 &
b00000000000000000000000000000110 '
b00000000000000000000000000000111 (
#35
0#
#36
1#
b01111111 &
b00000000000000000000000000000111 '
b00000000000000000000000000001000 (
#37
0#
#38
1#
b11111111 &
b00000000000000000000000000001000 '
b00000000000000000000000000000000 (
#39
0#
#40
1#
b00000000 &
b00000000000000000000000000000000 '
b00000000000000000000000000000001 (
#41
0#
#42
1#
b00000001 &
b00000000000000000000000000000001 '
b00000000000000000000000000000010 (
#43
0#
#44
1#
b00000011 &
b00000000000000000000000000000010 '
b00000000000000000000000000000011 (
#45
0#
#46
1#
b00000111 &
b00000000000000000000000000000011 '
b00000000000000000000000000000100 (
#47
0#
#48
1#
b00001111 &
b00000000000000000000000000000100 '
b00000000000000000000000000000101 (
#49
0#
#50
1#
b00011111 &
b00000000000000000000000000000101 '
b00000000000000000000000000000110 (
#51
0#
#52
1#
b00111111 &
b00000000000000000000000000000110 '
b00000000000000000000000000000111 (
#53
0#
#54
1#
b01111111 &
b00000000000000000000000000000111 '
b00000000000000000000000000001000 (
#55
0#
#56
1#
b11111111 &
b00000000000000000000000000001000 '
b00000000000000000000000000000000 (
#57
0#
#58
1#
b00000000 &
b00000000000000000000000000000000 '
b00000000000000000000000000000001 (
#59
0#
#60
1#
b00000001 &
b00000000000000000000000000000001 '
b00000000000000000000000000000010 (
#61
0#
#62
1#
b00000011 &
b00000000000000000000000000000010 '
b00000000000000000000000000000011 (
#63
0#
#64
1#
b00000111 &
b00000000000000000000000000000011 '
b00000000000000000000000000000100 (
#65
0#
#66
1#
b00001111 &
b00000000000000000000000000000100 '
b00000000000000000000000000000101 (
#67
0#
#68
1#
b00011111 &
b00000000000000000000000000000101 '
b00000000000000000000000000000110 (
#69
0#
#70
1#
b00111111 &
b00000000000000000000000000000110 '
b00000000000000000000000000000111 (
#71
0#
#72
1#
b01111111 &
b00000000000000000000000000000111 '
b00000000000000000000000000001000 (
#73
0#
#74
1#
b11111111 &
b00000000000000000000000000001000 '
b00000000000000000000000000000000 (
#75
0#
#76
1#
b00000000 &
b00000000000000000000000000000000 '
b00000000000000000000000000000001 (
#77
0#
#78
1#
b00000001 &
b00000000000000000000000000000001 '
b00000000000000000000000000000010 (
#79
0#
#80
1#
b00000011 &
b00000000000000000000000000000010 '
b00000000000000000000000000000011 (
#81
0#
#82
1#
b00000111 &
b00000000000000000000000000000011 '
b00000000000000000000000000000100 (
#83
0#
#84
1#
b00001111 &
b00000000000000000000000000000100 '
b00000000000000000000000000000101 (
#85
0#
#86
1#
b00011111 &
b00000000000000000000000000000101 '
b00000000000000000000000000000110 (
#87
0#
#88
1#
b00111111 &
b00000000000000000000000000000110 '
b00000000000000000000000000000111 (
#89
0#
#90
1#
b01111111 &
b00000000000000000000000000000111 '
b00000000000000000000000000001000 (
#91
0#
#92
1#
b11111111 &
b00000000000000000000000000001000 '
b00000000000000000000000000000000 (
#93
0#
#94
1#
b00000000 &
b00000000000000000000000000000000 '
b00000000000000000000000000000001 (
#95
0#
#96
1#
b00000001 &
b00000000000000000000000000000001 '
b00000000000000000000000000000010 (
#97
0#
#98
1#
b00000011 &
b00000000000000000000000000000010 '
b00000000000000000000000000000011 (
#99
0#
#100
1#
b00000111 &
b00000000000000000000000000000011 '
b00000000000000000000000000000100 (
#101
0#
#102
1#
b00001111 &
b00000000000000000000000000000100 '
b00000000000000000000000000000101 (
#103
0#
#104
1#
b00011111 &
b00000000000000000000000000000101 '
b00000000000000000000000000000110 (
#105
0#
#106
1#
b00111111 &
b00000000000000000000000000000110 '
b00000000000000000000000000000111 (
#107
0#
#108
1#
b01111111 &
b00000000000000000000000000000111 '
b00000000000000000000000000001000 (
#109
0#
#110
1#
b11111111 &
b00000000000000000000000000001000 '
b00000000000000000000000000000000 (
#111
0#
#112
1#
b00000000 &
b00000000000000000000000000000000 '
b00000000000000000000000000000001 (
#113
0#
#114
1#
b00000001 &
b00000000000000000000000000000001 '
b00000000000000000000000000000010 (
#115
0#
#116
1#
b00000011 &
b00000000000000000000000000000010 '
b00000000000000000000000000000011 (
#117
0#
#118
1#
b00000111 &
b00000000000000000000000000000011 '
b00000000000000000000000000000100 (
#119
0#
#120
1#
b00001111 &
b00000000000000000000000000000100 '
b00000000000000000000000000000101 (
#121
0#
#122
1#
b00011111 &
b00000000000000000000000000000101 '
b00000000000000000000000000000110 (
#123
0#
#124
1#
b00111111 &
b00000000000000000000000000000110 '
b00000000000000000000000000000111 (
#125
0#
#126
1#
b01111111 &
b00000000000000000000000000000111 '
b00000000000000000000000000001000 (
#127
0#
#128
1#
b11111111 &
b00000000000000000000000000001000 '
b00000000000000000000000000000000 (
#129
0#
#130
1#
b00000000 &
b00000000000000000000000000000000 '
b00000000000000000000000000000001 (
#131
0#
#132
1#
b00000001 &
b00000000000000000000000000000001 '
b00000000000000000000000000000010 (
#133
0#
#134
1#
b00000011 &
b00000000000000000000000000000010 '
b00000000000000000000000000000011 (
#135
0#
#136
1#
b00000111 &
b00000000000000000000000000000011 '
b00000000000000000000000000000100 (
#137
0#
#138
1#
b00001111 &
b00000000000000000000000000000100 '
b00000000000000000000000000000101 (
#139
0#
#140
1#
b00011111 &
b00000000000000000000000000000101 '
b00000000000000000000000000000110 (
#141
0#
#142
1#
b00111111 &
b00000000000000000000000000000110 '
b00000000000000000000000000000111 (
#143
0#
#144
1#
b01111111 &
b00000000000000000000000000000111 '
b00000000000000000000000000001000 (
#145
0#
#146
1#
b11111111 &
b00000000000000000000000000001000 '
b00000000000000000000000000000000 (
#147
0#
#148
1#
b00000000 &
b00000000000000000000000000000000 '
b00000000000000000000000000000001 (
#149
0#
#150
1#
b00000001 &
b00000000000000000000000000000001 '
b00000000000000000000000000000010 (
#151
0#
#152
1#
b00000011 &
b00000000000000000000000000000010 '
b00000000000000000000000000000011 (
#153
0#
#154
1#
b00000111 &
b00000000000000000000000000000011 '
b00000000000000000000000000000100 (
#155
0#
#156
1#
b00001111 &
b00000000000000000000000000000100 '
b00000000000000000000000000000101 (
#157
0#
#158
1#
b00011111 &
b00000000000000000000000000000101 '
b00000000000000000000000000000110 (
#159
0#
#160
1#
b00111111 &
b00000000000000000000000000000110 '
b00000000000000000000000000000111 (
#161
0#
#162
1#
b01111111 &
b00000000000000000000000000000111 '
b00000000000000000000000000001000 (
#163
0#
#164
1#
b11111111 &
b00000000000000000000000000001000 '
b00000000000000000000000000000000 (
#165
0#
#166
1#
b00000000 &
b00000000000000000000000000000000 '
b00000000000000000000000000000001 (
#167
0#
#168
1#
b00000001 &
b00000000000000000000000000000001 '
b00000000000000000000000000000010 (
#169
0#
#170
1#
b00000011 &
b00000000000000000000000000000010 '
b00000000000000000000000000000011 (
#171
0#
#172
1#
b00000111 &
b00000000000000000000000000000011 '
b00000000000000000000000000000100 (
#173
0#
#174
1#
b00001111 &
b00000000000000000000000000000100 '
b00000000000000000000000000000101 (
#175
0#
#176
1#
b00011111 &
b00000000000000000000000000000101 '
b00000000000000000000000000000110 (
#177
0#
#178
1#
b00111111 &
b00000000000000000000000000000110 '
b00000000000000000000000000000111 (
#179
0#
#180
1#
b01111111 &
b00000000000000000000000000000111 '
b00000000000000000000000000001000 (
#181
0#
#182
1#
b11111111 &
b00000000000000000000000000001000 '
b00000000000000000000000000000000 (
#183
0#
#184
1#
b00000000 &
b00000000000000000000000000000000 '
b00000000000000000000000000000001 (
#185
0#
#186
1#
b00000001 &
b00000000000000000000000000000001 '
b00000000000000000000000000000010 (
#187
0#
#188
1#
b00000011 &
b00000000000000000000000000000010 '
b00000000000000000000000000000011 (
#189
0#
#190
1#
b00000111 &
b00000000000000000000000000000011 '
b00000000000000000000000000000100 (
#191
0#
#192
1#
b00001111 &
b00000000000000000000000000000100 '
b00000000000000000000000000000101 (
#193
0#
#194
1#
b00011111 &
b00000000000000000000000000000101 '
b00000000000000000000000000000110 (
#195
0#
#196
1#
b00111111 &
b00000000000000000000000000000110 '
b00000000000000000000000000000111 (
#197
0#
#198
1#
b01111111 &
b00000000000000000000000000000111 '
b00000000000000000000000000001000 (
